django_mediawiki_auth-0.0.2.dist-info/DESCRIPTION.rst
django_mediawiki_auth-0.0.2.dist-info/METADATA
django_mediawiki_auth-0.0.2.dist-info/RECORD
django_mediawiki_auth-0.0.2.dist-info/WHEEL
django_mediawiki_auth-0.0.2.dist-info/metadata.json
django_mediawiki_auth-0.0.2.dist-info/top_level.txt
mediawiki_auth/__init__.py
mediawiki_auth/admin.py
mediawiki_auth/mediawiki.py
mediawiki_auth/middleware.py
mediawiki_auth/models.py
