Metadata-Version: 2.0
Name: django-mediawiki-auth
Version: 0.0.2
Summary: Django uses MediaWiki session to seamlessly authenticate users.
Home-page: https://github.com/damoti/django-mediawiki-auth
Author: Lex Berezhny
Author-email: lex@damoti.com
License: BSD
Keywords: django,mediawiki,wiki,wikipedia,php,session,auth
Platform: UNKNOWN
Classifier: Framework :: Django
Classifier: Intended Audience :: Developers
Classifier: License :: OSI Approved :: BSD License
Classifier: Programming Language :: Python :: 3
Classifier: Operating System :: OS Independent
Classifier: Topic :: Software Development :: Libraries :: Python Modules
Requires-Dist: phpserialize
